Workbook

Sheet InformacoesBasicas
A1: Esta planilha irá ajudá-lo(a) a preparar o planejamento financeiro para a sua startup. É uma planilha simplificada que exige pouca familiaridade com contabilidade ou finanças. Preencha todos os campos em "VERDE". Utilize apenas a última planilha "Resumo - Planejamento Financeiro" para demonstrar a viabilidade e lucratividade do seu empreendimento.
A9: Nome da Empresa: | C9: Empresa XYZ
A10: Atividade: | B10: 2 | C10: 1 para Comércio
C11: 2 para Serviços
C12: 3 para Indústria
A15: =IF(B10=2,"Nomes dos serviços que sua empresa irá vender","Nome dos produtos que sua empresa irá vender") -> Nomes dos serviços que sua empresa irá vender
A16: =IF(B$10=2,"Serviço","Produto") -> Serviço | B16: 1 | C16: produto 1
A17: =IF(B$10=2,"Serviço","Produto") -> Serviço | B17: 2 | C17: produto 2
A18: =IF(B$10=2,"Serviço","Produto") -> Serviço | B18: 3 | C18: produto 3
A19: =IF(B$10=2,"Serviço","Produto") -> Serviço | B19: 4 | C19: produto 4
A20: =IF(B$10=2,"Serviço","Produto") -> Serviço | B20: 5 | C20: produto 5
A21: =IF(B$10=2,"Serviço","Produto") -> Serviço | B21: 6 | C21: produto 6
A22: =IF(B$10=2,"Serviço","Produto") -> Serviço | B22: 7 | C22: produto 7
A23: =IF(B$10=2,"Serviço","Produto") -> Serviço | B23: 8 | C23: produto 8
A24: =IF(B$10=2,"Serviço","Produto") -> Serviço | B24: 9 | C24: produto 9
A25: =IF(B$10=2,"Serviço","Produto") -> Serviço | B25: 10 | C25: produto 10
A28: Estimativa de crescimento das vendas
A29: Crescimento das vendas no Ano 02 | D29: 0.15
A30: Crescimento das vendas no Ano 03 | D30: 0.25
A31: Crescimento das vendas no Ano 04 | D31: 0.4
A32: Crescimento das vendas no Ano 05 | D32: 0.6
A35: Estimativa de reajustes nas despesas
A36: Reajustes nas despesas no Ano 02 | D36: 0.1
A37: Reajustes nas despesas no Ano 03 | D37: 0.15
A38: Reajustes nas despesas no Ano 04 | D38: 0.15
A39: Reajustes nas despesas no Ano 05 | D39: 0.15
A42: Estimativa de reajustes nos custos
A43: Reajustes nas despesas no Ano 02 | D43: 0.1
A44: Reajustes nas despesas no Ano 03 | D44: 0.15
A45: Reajustes nas despesas no Ano 04 | D45: 0.2
A46: Reajustes nas despesas no Ano 05 | D46: 0.25

Sheet Entrada de $
A1: Planilha para Projeção de Vendas: Previsão de lançamento em 1 Marca com 2 Escritórios
A2: Valor Representativo da venda da solução : Plataforma (softwares) + Máquinas (hardwares) com percentual de Fee Mensal dos produtos tecnológicos oferecidos
A4: Mês | B4: 1 | C4: 2 | D4: 3 | E4: 4 | F4: 5 | G4: 6 | H4: 7 | I4: 8 | J4: 9 | K4: 10 | L4: 11 | M4: 12 | N4: Vendas - Ano 01
A5: Vendas Totais | B5: =B7+B11+B15+B19+B23+B27+B31+B35+B39+B43 -> 33875 | C5: =C7+C11+C15+C19+C23+C27+C31+C35+C39+C43 -> 52125 | D5: =D7+D11+D15+D19+D23+D27+D31+D35+D39+D43 -> 58025 | E5: =E7+E11+E15+E19+E23+E27+E31+E35+E39+E43 -> 67025 | F5: =F7+F11+F15+F19+F23+F27+F31+F35+F39+F43 -> 69575 | G5: =G7+G11+G15+G19+G23+G27+G31+G35+G39+G43 -> 73575 | H5: =H7+H11+H15+H19+H23+H27+H31+H35+H39+H43 -> 78850 | I5: =I7+I11+I15+I19+I23+I27+I31+I35+I39+I43 -> 86550 | ... M5: =M7+M11+M15+M19+M23+M27+M31+M35+M39+M43 -> 119450 | N5: =SUM(B5:M5) -> 947100
A7: ="Vendas de "&InformacoesBasicas!C16 -> Vendas de produto 1 | B7: =B8*B9 -> 200 | C7: =C8*C9 -> 500 | D7: =D8*D9 -> 750 | E7: =E8*E9 -> 1000 | F7: =F8*F9 -> 1200 | G7: =G8*G9 -> 2000 | H7: =H8*H9 -> 2000 | I7: =I8*I9 -> 2000 | ... M7: =M8*M9 -> 2800 | N7: =SUM(B7:M7) -> 18950
A8: Itens vendidos | B8: 20 | C8: 50 | D8: 75 | E8: 100 | F8: 120 | G8: 200 | H8: 200 | I8: 200 | J8: 200 | K8: 200 | L8: 250 | M8: 280 | N8: =SUM(B8:M8) -> 1895
A9: ="Preço de "&InformacoesBasicas!C16 -> Preço de produto 1 | B9: 10 | C9: 10 | D9: 10 | E9: 10 | F9: 10 | G9: 10 | H9: 10 | I9: 10 | J9: 10 | K9: 10 | L9: 10 | M9: 10 | N9: =SUM(B9:M9) -> 120
A10: Dashboard
A11: ="Vendas de "&InformacoesBasicas!C17 -> Vendas de produto 2 | B11: =B12*B13 -> 300 | C11: =C12*C13 -> 1000 | D11: =D12*D13 -> 1000 | E11: =E12*E13 -> 1400 | F11: =F12*F13 -> 1500 | G11: =G12*G13 -> 2200 | H11: =H12*H13 -> 2200 | I11: =I12*I13 -> 2200 | ... M11: =M12*M13 -> 6000 | N11: =SUM(B11:M11) -> 29800
A12: Itens vendidos | B12: 15 | C12: 50 | D12: 50 | E12: 70 | F12: 75 | G12: 110 | H12: 110 | I12: 110 | J12: 150 | K12: 200 | L12: 250 | M12: 300 | N12: =SUM(B12:M12) -> 1490
A13: ="Preço de "&InformacoesBasicas!C17 -> Preço de produto 2 | B13: 20 | C13: 20 | D13: 20 | E13: 20 | F13: 20 | G13: 20 | H13: 20 | I13: 20 | J13: 20 | K13: 20 | L13: 20 | M13: 20 | N13: =SUM(B13:M13) -> 240
A15: ="Vendas de "&InformacoesBasicas!C18 -> Vendas de produto 3 | B15: =B16*B17 -> 0 | C15: =C16*C17 -> 600 | D15: =D16*D17 -> 1500 | E15: =E16*E17 -> 2400 | F15: =F16*F17 -> 2700 | G15: =G16*G17 -> 2700 | H15: =H16*H17 -> 2700 | I15: =I16*I17 -> 3300 | ... M15: =M16*M17 -> 7500 | N15: =SUM(B15:M15) -> 37800
A16: Itens vendidos | B16: 0 | C16: 20 | D16: 50 | E16: 80 | F16: 90 | G16: 90 | H16: 90 | I16: 110 | J16: 110 | K16: 150 | L16: 220 | M16: 250 | N16: =SUM(B16:M16) -> 1260
A17: ="Preço de "&InformacoesBasicas!C18 -> Preço de produto 3 | B17: 30 | C17: 30 | D17: 30 | E17: 30 | F17: 30 | G17: 30 | H17: 30 | I17: 30 | J17: 30 | K17: 30 | L17: 30 | M17: 30 | N17: =SUM(B17:M17) -> 360
A19: ="Vendas de "&InformacoesBasicas!C19 -> Vendas de produto 4 | B19: =B20*B21 -> 0 | C19: =C20*C21 -> 1600 | D19: =D20*D21 -> 1600 | E19: =E20*E21 -> 2000 | F19: =F20*F21 -> 2400 | G19: =G20*G21 -> 2400 | H19: =H20*H21 -> 2400 | I19: =I20*I21 -> 4800 | ... M19: =M20*M21 -> 18000 | N19: =SUM(B19:M19) -> 58400
A20: Itens vendidos | B20: 0 | C20: 40 | D20: 40 | E20: 50 | F20: 60 | G20: 60 | H20: 60 | I20: 120 | J20: 180 | K20: 200 | L20: 200 | M20: 200 | N20: =SUM(B20:M20) -> 1210
A21: ="Preço de "&InformacoesBasicas!C19 -> Preço de produto 4 | B21: 40 | C21: 40 | D21: 40 | E21: 40 | F21: 40 | G21: 40 | H21: 40 | I21: 40 | J21: 40 | K21: 40 | L21: 40 | M21: 90 | N21: =SUM(B21:M21) -> 530
A23: ="Vendas de "&InformacoesBasicas!C20 -> Vendas de produto 5 | B23: =B24*B25 -> 4000 | C23: =C24*C25 -> 5000 | D23: =D24*D25 -> 6000 | E23: =E24*E25 -> 7500 | F23: =F24*F25 -> 7500 | G23: =G24*G25 -> 10000 | H23: =H24*H25 -> 11000 | I23: =I24*I25 -> 11000 | ... M23: =M24*M25 -> 15000 | N23: =SUM(B23:M23) -> 115500
A24: Itens vendidos | B24: 80 | C24: 100 | D24: 120 | E24: 150 | F24: 150 | G24: 200 | H24: 220 | I24: 220 | J24: 220 | K24: 250 | L24: 300 | M24: 300 | N24: =SUM(B24:M24) -> 2310
A25: ="Preço de "&InformacoesBasicas!C20 -> Preço de produto 5 | B25: 50 | C25: 50 | D25: 50 | E25: 50 | F25: 50 | G25: 50 | H25: 50 | I25: 50 | J25: 50 | K25: 50 | L25: 50 | M25: 50 | N25: =SUM(B25:M25) -> 600
A27: ="Vendas de "&InformacoesBasicas!C21 -> Vendas de produto 6 | B27: =B28*B29 -> 0 | C27: =C28*C29 -> 7000 | D27: =D28*D29 -> 8400 | E27: =E28*E29 -> 9100 | F27: =F28*F29 -> 8400 | G27: =G28*G29 -> 8400 | H27: =H28*H29 -> 8400 | I27: =I28*I29 -> 8400 | ... M27: =M28*M29 -> 12600 | N27: =SUM(B27:M27) -> 104300
A28: Itens vendidos | B28: 0 | C28: 100 | D28: 120 | E28: 130 | F28: 120 | G28: 120 | H28: 120 | I28: 120 | J28: 150 | K28: 150 | L28: 180 | M28: 180 | N28: =SUM(B28:M28) -> 1490
A29: ="Preço de "&InformacoesBasicas!C21 -> Preço de produto 6 | B29: 70 | C29: 70 | D29: 70 | E29: 70 | F29: 70 | G29: 70 | H29: 70 | I29: 70 | J29: 70 | K29: 70 | L29: 70 | M29: 70 | N29: =SUM(B29:M29) -> 840
A31: ="Vendas de "&InformacoesBasicas!C22 -> Vendas de produto 7 | B31: =B32*B33 -> 0 | C31: =C32*C33 -> 2250 | D31: =D32*D33 -> 3000 | E31: =E32*E33 -> 4875 | F31: =F32*F33 -> 4875 | G31: =G32*G33 -> 4875 | H31: =H32*H33 -> 6750 | I31: =I32*I33 -> 6750 | ... M31: =M32*M33 -> 7500 | N31: =SUM(B31:M31) -> 62625
A32: Itens vendidos | B32: 0 | C32: 30 | D32: 40 | E32: 65 | F32: 65 | G32: 65 | H32: 90 | I32: 90 | J32: 90 | K32: 100 | L32: 100 | M32: 100 | N32: =SUM(B32:M32) -> 835
A33: ="Preço de "&InformacoesBasicas!C25 -> Preço de produto 10 | B33: 75 | C33: 75 | D33: 75 | E33: 75 | F33: 75 | G33: 75 | H33: 75 | I33: 75 | J33: 75 | K33: 75 | L33: 75 | M33: 75 | N33: =SUM(B33:M33) -> 900
A35: ="Vendas de "&InformacoesBasicas!C23 -> Vendas de produto 8 | B35: =B36*B37 -> 6375 | C35: =C36*C37 -> 6375 | D35: =D36*D37 -> 6375 | E35: =E36*E37 -> 9350 | F35: =F36*F37 -> 8500 | G35: =G36*G37 -> 8500 | H35: =H36*H37 -> 8500 | I35: =I36*I37 -> 8500 | ... M35: =M36*M37 -> 11050 | N35: =SUM(B35:M35) -> 102425
A36: Itens vendidos | B36: 75 | C36: 75 | D36: 75 | E36: 110 | F36: 100 | G36: 100 | H36: 100 | I36: 100 | J36: 100 | K36: 120 | L36: 120 | M36: 130 | N36: =SUM(B36:M36) -> 1205
A37: ="Preço de "&InformacoesBasicas!C29 -> Preço de | B37: 85 | C37: 85 | D37: 85 | E37: 85 | F37: 85 | G37: 85 | H37: 85 | I37: 85 | J37: 85 | K37: 85 | L37: 85 | M37: 85 | N37: =SUM(B37:M37) -> 1020
A39: ="Vendas de "&InformacoesBasicas!C24 -> Vendas de produto 9 | B39: =B40*B41 -> 0 | C39: =C40*C41 -> 4800 | D39: =D40*D41 -> 6400 | E39: =E40*E41 -> 6400 | F39: =F40*F41 -> 7200 | G39: =G40*G41 -> 7200 | H39: =H40*H41 -> 9600 | I39: =I40*I41 -> 12000 | ... M39: =M40*M41 -> 16000 | N39: =SUM(B39:M39) -> 116000
A40: Itens vendidos | B40: 0 | C40: 30 | D40: 40 | E40: 40 | F40: 45 | G40: 45 | H40: 60 | I40: 75 | J40: 90 | K40: 100 | L40: 100 | M40: 100 | N40: =SUM(B40:M40) -> 725
A41: ="Preço de "&InformacoesBasicas!C33 -> Preço de | B41: 160 | C41: 160 | D41: 160 | E41: 160 | F41: 160 | G41: 160 | H41: 160 | I41: 160 | J41: 160 | K41: 160 | L41: 160 | M41: 160 | N41: =SUM(B41:M41) -> 1920
A43: ="Vendas de "&InformacoesBasicas!C25 -> Vendas de produto 10 | B43: =B44*B45 -> 23000 | C43: =C44*C45 -> 23000 | D43: =D44*D45 -> 23000 | E43: =E44*E45 -> 23000 | F43: =F44*F45 -> 25300 | G43: =G44*G45 -> 25300 | H43: =H44*H45 -> 25300 | I43: =I44*I45 -> 27600 | ... M43: =M44*M45 -> 23000 | N43: =SUM(B43:M43) -> 301300
A44: Itens vendidos | B44: 100 | C44: 100 | D44: 100 | E44: 100 | F44: 110 | G44: 110 | H44: 110 | I44: 120 | J44: 120 | K44: 120 | L44: 120 | M44: 100 | N44: =SUM(B44:M44) -> 1310
A45: ="Preço de "&InformacoesBasicas!C37 -> Preço de | B45: 230 | C45: 230 | D45: 230 | E45: 230 | F45: 230 | G45: 230 | H45: 230 | I45: 230 | J45: 230 | K45: 230 | L45: 230 | M45: 230 | N45: =SUM(B45:M45) -> 2760

Sheet Custo Unitário
A1: Planilha para Cálculo do Custo Unitário
A4: =IF(InformacoesBasicas!B10=1,"Custo Unitário de Aquisição do Fornecedor de ",IF(InformacoesBasicas!B10=2,"Custo Unitário de Prestação de cada Serviço de ",IF(InformacoesBasicas!B10=3,"Custo da matéria-prima para Fabricação de cada ","Custo de")))&InformacoesBasicas!C16 -> Custo Unitário de Prestação de cada Serviço de produto 1 | B4: 15
A6: =IF(InformacoesBasicas!B10=1,"Custo Unitário de Aquisição do Fornecedor de ",IF(InformacoesBasicas!B10=2,"Custo Unitário de Prestação de cada Serviço de ",IF(InformacoesBasicas!B10=3,"Custo da matéria-prima para Fabricação de cada ","Custo de")))&InformacoesBasicas!C17 -> Custo Unitário de Prestação de cada Serviço de produto 2 | B6: 20
A8: =IF(InformacoesBasicas!B10=1,"Custo Unitário de Aquisição do Fornecedor de ",IF(InformacoesBasicas!B10=2,"Custo Unitário de Prestação de cada Serviço de ",IF(InformacoesBasicas!B10=3,"Custo da matéria-prima para Fabricação de cada ","Custo de")))&InformacoesBasicas!C18 -> Custo Unitário de Prestação de cada Serviço de produto 3 | B8: 25
A10: =IF(InformacoesBasicas!B10=1,"Custo Unitário de Aquisição do Fornecedor de ",IF(InformacoesBasicas!B10=2,"Custo Unitário de Prestação de cada Serviço de ",IF(InformacoesBasicas!B10=3,"Custo da matéria-prima para Fabricação de cada ","Custo de")))&InformacoesBasicas!C19 -> Custo Unitário de Prestação de cada Serviço de produto 4 | B10: 30
A12: =IF(InformacoesBasicas!B10=1,"Custo Unitário de Aquisição do Fornecedor de ",IF(InformacoesBasicas!B10=2,"Custo Unitário de Prestação de cada Serviço de ",IF(InformacoesBasicas!B10=3,"Custo da matéria-prima para Fabricação de cada ","Custo de")))&InformacoesBasicas!C20 -> Custo Unitário de Prestação de cada Serviço de produto 5 | B12: 35
A14: =IF(InformacoesBasicas!B10=1,"Custo Unitário de Aquisição do Fornecedor de ",IF(InformacoesBasicas!B10=2,"Custo Unitário de Prestação de cada Serviço de ",IF(InformacoesBasicas!B10=3,"Custo da matéria-prima para Fabricação de cada ","Custo de")))&InformacoesBasicas!C21 -> Custo Unitário de Prestação de cada Serviço de produto 6 | B14: 40
A16: =IF(InformacoesBasicas!B10=1,"Custo Unitário de Aquisição do Fornecedor de ",IF(InformacoesBasicas!B10=2,"Custo Unitário de Prestação de cada Serviço de ",IF(InformacoesBasicas!B10=3,"Custo da matéria-prima para Fabricação de cada ","Custo de")))&InformacoesBasicas!C22 -> Custo Unitário de Prestação de cada Serviço de produto 7 | B16: 45
A18: =IF(InformacoesBasicas!B10=1,"Custo Unitário de Aquisição do Fornecedor de ",IF(InformacoesBasicas!B10=2,"Custo Unitário de Prestação de cada Serviço de ",IF(InformacoesBasicas!B10=3,"Custo da matéria-prima para Fabricação de cada ","Custo de")))&InformacoesBasicas!C23 -> Custo Unitário de Prestação de cada Serviço de produto 8 | B18: 50
A20: =IF(InformacoesBasicas!B10=1,"Custo Unitário de Aquisição do Fornecedor de ",IF(InformacoesBasicas!B10=2,"Custo Unitário de Prestação de cada Serviço de ",IF(InformacoesBasicas!B10=3,"Custo da matéria-prima para Fabricação de cada ","Custo de")))&InformacoesBasicas!C24 -> Custo Unitário de Prestação de cada Serviço de produto 9 | B20: 55
A22: =IF(InformacoesBasicas!B10=1,"Custo Unitário de Aquisição do Fornecedor de ",IF(InformacoesBasicas!B10=2,"Custo Unitário de Prestação de cada Serviço de ",IF(InformacoesBasicas!B10=3,"Custo da matéria-prima para Fabricação de cada ","Custo de")))&InformacoesBasicas!C25 -> Custo Unitário de Prestação de cada Serviço de produto 10 | B22: 60

Sheet Calculo de Custo
A1: Planilha para Cálculo do Custo Total
A4: Mês | B4: 1 | C4: 2 | D4: 3 | E4: 4 | F4: 5 | G4: 6 | H4: 7 | I4: 8 | J4: 9 | K4: 10 | L4: 11 | M4: 12 | N4: Vendas - Ano 01
A5: Vendas Totais | B5: =B7+B11+B15+B19+B23+B27+B31+B35+B39+B43 -> 13150 | C5: =C7+C11+C15+C19+C23+C27+C31+C35+C39+C43 -> 23700 | D5: =D7+D11+D15+D19+D23+D27+D31+D35+D39+D43 -> 27325 | E5: =E7+E11+E15+E19+E23+E27+E31+E35+E39+E43 -> 33475 | F5: =F7+F11+F15+F19+F23+F27+F31+F35+F39+F43 -> 34400 | G5: =G7+G11+G15+G19+G23+G27+G31+G35+G39+G43 -> 38050 | H5: =H7+H11+H15+H19+H23+H27+H31+H35+H39+H43 -> 40700 | I5: =I7+I11+I15+I19+I23+I27+I31+I35+I39+I43 -> 44425 | ... N5: =N7+N11+N15+N19+N23+N27+N31+N35+N39+N43 -> 482775
A7: ="Custo Total de "&InformacoesBasicas!C16 -> Custo Total de produto 1 | B7: =B8*B9 -> 300 | C7: =C8*C9 -> 750 | D7: =D8*D9 -> 1125 | E7: =E8*E9 -> 1500 | F7: =F8*F9 -> 1800 | G7: =G8*G9 -> 3000 | H7: =H8*H9 -> 3000 | I7: =I8*I9 -> 3000 | ... M7: =M8*M9 -> 4200 | N7: =SUM(B7:M7) -> 28425
A8: =IF(InformacoesBasicas!B10=1,"Custo de Aquisição de ",IF(InformacoesBasicas!B10=2,"Custo de Prestação de Serviço de ",IF(InformacoesBasicas!B10=3,"Custo de Fabricação de ","Custo de")))&InformacoesBasicas!C16 -> Custo de Prestação de Serviço de produto 1 | B8: ='Custo Unitário'!B4 -> 15 | C8: =$B8 -> 15 | D8: =$B8 -> 15 | E8: =$B8 -> 15 | F8: =$B8 -> 15 | G8: =$B8 -> 15 | H8: =$B8 -> 15 | I8: =$B8 -> 15 | J8: =$B8 -> 15 | ... M8: =$B8 -> 15 | N8: =AVERAGE(B8:M8) -> 15
A9: Itens vendidos | B9: ='Entrada de $'!B8 -> 20 | C9: ='Entrada de $'!C8 -> 50 | D9: ='Entrada de $'!D8 -> 75 | E9: ='Entrada de $'!E8 -> 100 | F9: ='Entrada de $'!F8 -> 120 | G9: ='Entrada de $'!G8 -> 200 | H9: ='Entrada de $'!H8 -> 200 | I9: ='Entrada de $'!I8 -> 200 | ... M9: ='Entrada de $'!M8 -> 280 | N9: =SUM(B9:M9) -> 1895
A11: ="Custo Total de "&InformacoesBasicas!C17 -> Custo Total de produto 2 | B11: =B12*B13 -> 300 | C11: =C12*C13 -> 1000 | D11: =D12*D13 -> 1000 | E11: =E12*E13 -> 1400 | F11: =F12*F13 -> 1500 | G11: =G12*G13 -> 2200 | H11: =H12*H13 -> 2200 | I11: =I12*I13 -> 2200 | ... M11: =M12*M13 -> 6000 | N11: =SUM(B11:M11) -> 29800
A12: =IF(InformacoesBasicas!B10=1,"Custo de Aquisição de ",IF(InformacoesBasicas!B10=2,"Custo de Prestação de Serviço de ",IF(InformacoesBasicas!B10=3,"Custo de Fabricação de ","Custo de")))&InformacoesBasicas!C17 -> Custo de Prestação de Serviço de produto 2 | B12: ='Custo Unitário'!B6 -> 20 | C12: =$B12 -> 20 | D12: =$B12 -> 20 | E12: =$B12 -> 20 | F12: =$B12 -> 20 | G12: =$B12 -> 20 | H12: =$B12 -> 20 | I12: =$B12 -> 20 | J12: =$B12 -> 20 | ... M12: =$B12 -> 20 | N12: =AVERAGE(B12:M12) -> 20
A13: Itens vendidos | B13: ='Entrada de $'!B12 -> 15 | C13: ='Entrada de $'!C12 -> 50 | D13: ='Entrada de $'!D12 -> 50 | E13: ='Entrada de $'!E12 -> 70 | F13: ='Entrada de $'!F12 -> 75 | G13: ='Entrada de $'!G12 -> 110 | H13: ='Entrada de $'!H12 -> 110 | I13: ='Entrada de $'!I12 -> 110 | ... M13: ='Entrada de $'!M12 -> 300 | N13: =SUM(B13:M13) -> 1490
A15: ="Custo Total de "&InformacoesBasicas!C18 -> Custo Total de produto 3 | B15: =B16*B17 -> 0 | C15: =C16*C17 -> 500 | D15: =D16*D17 -> 1250 | E15: =E16*E17 -> 2000 | F15: =F16*F17 -> 2250 | G15: =G16*G17 -> 2250 | H15: =H16*H17 -> 2250 | I15: =I16*I17 -> 2750 | ... M15: =M16*M17 -> 6250 | N15: =SUM(B15:M15) -> 31500
A16: =IF(InformacoesBasicas!B10=1,"Custo de Aquisição de ",IF(InformacoesBasicas!B10=2,"Custo de Prestação de Serviço de ",IF(InformacoesBasicas!B10=3,"Custo de Fabricação de ","Custo de")))&InformacoesBasicas!C18 -> Custo de Prestação de Serviço de produto 3 | B16: ='Custo Unitário'!B8 -> 25 | C16: =$B16 -> 25 | D16: =$B16 -> 25 | E16: =$B16 -> 25 | F16: =$B16 -> 25 | G16: =$B16 -> 25 | H16: =$B16 -> 25 | I16: =$B16 -> 25 | J16: =$B16 -> 25 | ... M16: =$B16 -> 25 | N16: =AVERAGE(B16:M16) -> 25
A17: Itens vendidos | B17: ='Entrada de $'!B16 -> 0 | C17: ='Entrada de $'!C16 -> 20 | D17: ='Entrada de $'!D16 -> 50 | E17: ='Entrada de $'!E16 -> 80 | F17: ='Entrada de $'!F16 -> 90 | G17: ='Entrada de $'!G16 -> 90 | H17: ='Entrada de $'!H16 -> 90 | I17: ='Entrada de $'!I16 -> 110 | ... M17: ='Entrada de $'!M16 -> 250 | N17: =SUM(B17:M17) -> 1260
A19: ="Custo Total de "&InformacoesBasicas!C19 -> Custo Total de produto 4 | B19: =B20*B21 -> 0 | C19: =C20*C21 -> 1200 | D19: =D20*D21 -> 1200 | E19: =E20*E21 -> 1500 | F19: =F20*F21 -> 1800 | G19: =G20*G21 -> 1800 | H19: =H20*H21 -> 1800 | I19: =I20*I21 -> 3600 | ... M19: =M20*M21 -> 6000 | N19: =SUM(B19:M19) -> 36300
A20: =IF(InformacoesBasicas!B10=1,"Custo de Aquisição de ",IF(InformacoesBasicas!B10=2,"Custo de Prestação de Serviço de ",IF(InformacoesBasicas!B10=3,"Custo de Fabricação de ","Custo de")))&InformacoesBasicas!C19 -> Custo de Prestação de Serviço de produto 4 | B20: ='Custo Unitário'!B10 -> 30 | C20: =$B20 -> 30 | D20: =$B20 -> 30 | E20: =$B20 -> 30 | F20: =$B20 -> 30 | G20: =$B20 -> 30 | H20: =$B20 -> 30 | I20: =$B20 -> 30 | J20: =$B20 -> 30 | ... M20: =$B20 -> 30 | N20: =AVERAGE(B20:M20) -> 30
A21: Itens vendidos | B21: ='Entrada de $'!B20 -> 0 | C21: ='Entrada de $'!C20 -> 40 | D21: ='Entrada de $'!D20 -> 40 | E21: ='Entrada de $'!E20 -> 50 | F21: ='Entrada de $'!F20 -> 60 | G21: ='Entrada de $'!G20 -> 60 | H21: ='Entrada de $'!H20 -> 60 | I21: ='Entrada de $'!I20 -> 120 | ... M21: ='Entrada de $'!M20 -> 200 | N21: =SUM(B21:M21) -> 1210
A23: ="Custo Total de "&InformacoesBasicas!C20 -> Custo Total de produto 5 | B23: =B24*B25 -> 2800 | C23: =C24*C25 -> 3500 | D23: =D24*D25 -> 4200 | E23: =E24*E25 -> 5250 | F23: =F24*F25 -> 5250 | G23: =G24*G25 -> 7000 | H23: =H24*H25 -> 7700 | I23: =I24*I25 -> 7700 | ... M23: =M24*M25 -> 10500 | N23: =SUM(B23:M23) -> 80850
A24: =IF(InformacoesBasicas!B10=1,"Custo de Aquisição de ",IF(InformacoesBasicas!B10=2,"Custo de Prestação de Serviço de ",IF(InformacoesBasicas!B10=3,"Custo de Fabricação de ","Custo de")))&InformacoesBasicas!C20 -> Custo de Prestação de Serviço de produto 5 | B24: ='Custo Unitário'!B12 -> 35 | C24: =$B24 -> 35 | D24: =$B24 -> 35 | E24: =$B24 -> 35 | F24: =$B24 -> 35 | G24: =$B24 -> 35 | H24: =$B24 -> 35 | I24: =$B24 -> 35 | J24: =$B24 -> 35 | ... M24: =$B24 -> 35 | N24: =AVERAGE(B24:M24) -> 35
A25: Itens vendidos | B25: ='Entrada de $'!B24 -> 80 | C25: ='Entrada de $'!C24 -> 100 | D25: ='Entrada de $'!D24 -> 120 | E25: ='Entrada de $'!E24 -> 150 | F25: ='Entrada de $'!F24 -> 150 | G25: ='Entrada de $'!G24 -> 200 | H25: ='Entrada de $'!H24 -> 220 | I25: ='Entrada de $'!I24 -> 220 | ... M25: ='Entrada de $'!M24 -> 300 | N25: =SUM(B25:M25) -> 2310
A27: ="Custo Total de "&InformacoesBasicas!C21 -> Custo Total de produto 6 | B27: =B28*B29 -> 0 | C27: =C28*C29 -> 4000 | D27: =D28*D29 -> 4800 | E27: =E28*E29 -> 5200 | F27: =F28*F29 -> 4800 | G27: =G28*G29 -> 4800 | H27: =H28*H29 -> 4800 | I27: =I28*I29 -> 4800 | ... M27: =M28*M29 -> 7200 | N27: =SUM(B27:M27) -> 59600
A28: =IF(InformacoesBasicas!B10=1,"Custo de Aquisição de ",IF(InformacoesBasicas!B10=2,"Custo de Prestação de Serviço de ",IF(InformacoesBasicas!B10=3,"Custo de Fabricação de ","Custo de")))&InformacoesBasicas!C21 -> Custo de Prestação de Serviço de produto 6 | B28: ='Custo Unitário'!B14 -> 40 | C28: =$B28 -> 40 | D28: =$B28 -> 40 | E28: =$B28 -> 40 | F28: =$B28 -> 40 | G28: =$B28 -> 40 | H28: =$B28 -> 40 | I28: =$B28 -> 40 | J28: =$B28 -> 40 | ... M28: =$B28 -> 40 | N28: =AVERAGE(B28:M28) -> 40
A29: Itens vendidos | B29: ='Entrada de $'!B28 -> 0 | C29: ='Entrada de $'!C28 -> 100 | D29: ='Entrada de $'!D28 -> 120 | E29: ='Entrada de $'!E28 -> 130 | F29: ='Entrada de $'!F28 -> 120 | G29: ='Entrada de $'!G28 -> 120 | H29: ='Entrada de $'!H28 -> 120 | I29: ='Entrada de $'!I28 -> 120 | ... M29: ='Entrada de $'!M28 -> 180 | N29: =SUM(B29:M29) -> 1490
A31: ="Custo Total de "&InformacoesBasicas!C22 -> Custo Total de produto 7 | B31: =B32*B33 -> 0 | C31: =C32*C33 -> 1350 | D31: =D32*D33 -> 1800 | E31: =E32*E33 -> 2925 | F31: =F32*F33 -> 2925 | G31: =G32*G33 -> 2925 | H31: =H32*H33 -> 4050 | I31: =I32*I33 -> 4050 | ... M31: =M32*M33 -> 4500 | N31: =SUM(B31:M31) -> 37575
A32: =IF(InformacoesBasicas!B10=1,"Custo de Aquisição de ",IF(InformacoesBasicas!B10=2,"Custo de Prestação de Serviço de ",IF(InformacoesBasicas!B10=3,"Custo de Fabricação de ","Custo de")))&InformacoesBasicas!C22 -> Custo de Prestação de Serviço de produto 7 | B32: ='Custo Unitário'!B16 -> 45 | C32: =$B32 -> 45 | D32: =$B32 -> 45 | E32: =$B32 -> 45 | F32: =$B32 -> 45 | G32: =$B32 -> 45 | H32: =$B32 -> 45 | I32: =$B32 -> 45 | J32: =$B32 -> 45 | ... M32: =$B32 -> 45 | N32: =AVERAGE(B32:M32) -> 45
A33: Itens vendidos | B33: ='Entrada de $'!B32 -> 0 | C33: ='Entrada de $'!C32 -> 30 | D33: ='Entrada de $'!D32 -> 40 | E33: ='Entrada de $'!E32 -> 65 | F33: ='Entrada de $'!F32 -> 65 | G33: ='Entrada de $'!G32 -> 65 | H33: ='Entrada de $'!H32 -> 90 | I33: ='Entrada de $'!I32 -> 90 | ... M33: ='Entrada de $'!M32 -> 100 | N33: =SUM(B33:M33) -> 835
A35: ="Custo Total de "&InformacoesBasicas!C23 -> Custo Total de produto 8 | B35: =B36*B37 -> 3750 | C35: =C36*C37 -> 3750 | D35: =D36*D37 -> 3750 | E35: =E36*E37 -> 5500 | F35: =F36*F37 -> 5000 | G35: =G36*G37 -> 5000 | H35: =H36*H37 -> 5000 | I35: =I36*I37 -> 5000 | ... M35: =M36*M37 -> 6500 | N35: =SUM(B35:M35) -> 60250
A36: =IF(InformacoesBasicas!B10=1,"Custo de Aquisição de ",IF(InformacoesBasicas!B10=2,"Custo de Prestação de Serviço de ",IF(InformacoesBasicas!B10=3,"Custo de Fabricação de ","Custo de")))&InformacoesBasicas!C23 -> Custo de Prestação de Serviço de produto 8 | B36: ='Custo Unitário'!B18 -> 50 | C36: =$B36 -> 50 | D36: =$B36 -> 50 | E36: =$B36 -> 50 | F36: =$B36 -> 50 | G36: =$B36 -> 50 | H36: =$B36 -> 50 | I36: =$B36 -> 50 | J36: =$B36 -> 50 | ... M36: =$B36 -> 50 | N36: =AVERAGE(B36:M36) -> 50
A37: Itens vendidos | B37: ='Entrada de $'!B36 -> 75 | C37: ='Entrada de $'!C36 -> 75 | D37: ='Entrada de $'!D36 -> 75 | E37: ='Entrada de $'!E36 -> 110 | F37: ='Entrada de $'!F36 -> 100 | G37: ='Entrada de $'!G36 -> 100 | H37: ='Entrada de $'!H36 -> 100 | I37: ='Entrada de $'!I36 -> 100 | ... M37: ='Entrada de $'!M36 -> 130 | N37: =SUM(B37:M37) -> 1205
A39: ="Custo Total de "&InformacoesBasicas!C24 -> Custo Total de produto 9 | B39: =B40*B41 -> 0 | C39: =C40*C41 -> 1650 | D39: =D40*D41 -> 2200 | E39: =E40*E41 -> 2200 | F39: =F40*F41 -> 2475 | G39: =G40*G41 -> 2475 | H39: =H40*H41 -> 3300 | I39: =I40*I41 -> 4125 | ... M39: =M40*M41 -> 5500 | N39: =SUM(B39:M39) -> 39875
A40: =IF(InformacoesBasicas!B10=1,"Custo de Aquisição de ",IF(InformacoesBasicas!B10=2,"Custo de Prestação de Serviço de ",IF(InformacoesBasicas!B10=3,"Custo de Fabricação de ","Custo de")))&InformacoesBasicas!C24 -> Custo de Prestação de Serviço de produto 9 | B40: ='Custo Unitário'!B20 -> 55 | C40: =$B40 -> 55 | D40: =$B40 -> 55 | E40: =$B40 -> 55 | F40: =$B40 -> 55 | G40: =$B40 -> 55 | H40: =$B40 -> 55 | I40: =$B40 -> 55 | J40: =$B40 -> 55 | ... M40: =$B40 -> 55 | N40: =AVERAGE(B40:M40) -> 55
A41: Itens vendidos | B41: ='Entrada de $'!B40 -> 0 | C41: ='Entrada de $'!C40 -> 30 | D41: ='Entrada de $'!D40 -> 40 | E41: ='Entrada de $'!E40 -> 40 | F41: ='Entrada de $'!F40 -> 45 | G41: ='Entrada de $'!G40 -> 45 | H41: ='Entrada de $'!H40 -> 60 | I41: ='Entrada de $'!I40 -> 75 | ... M41: ='Entrada de $'!M40 -> 100 | N41: =SUM(B41:M41) -> 725
A43: ="Custo Total de "&InformacoesBasicas!C25 -> Custo Total de produto 10 | B43: =B44*B45 -> 6000 | C43: =C44*C45 -> 6000 | D43: =D44*D45 -> 6000 | E43: =E44*E45 -> 6000 | F43: =F44*F45 -> 6600 | G43: =G44*G45 -> 6600 | H43: =H44*H45 -> 6600 | I43: =I44*I45 -> 7200 | ... M43: =M44*M45 -> 6000 | N43: =SUM(B43:M43) -> 78600
A44: =IF(InformacoesBasicas!B10=1,"Custo de Aquisição de ",IF(InformacoesBasicas!B10=2,"Custo de Prestação de Serviço de ",IF(InformacoesBasicas!B10=3,"Custo de Fabricação de ","Custo de")))&InformacoesBasicas!C25 -> Custo de Prestação de Serviço de produto 10 | B44: ='Custo Unitário'!B22 -> 60 | C44: =$B44 -> 60 | D44: =$B44 -> 60 | E44: =$B44 -> 60 | F44: =$B44 -> 60 | G44: =$B44 -> 60 | H44: =$B44 -> 60 | I44: =$B44 -> 60 | J44: =$B44 -> 60 | ... M44: =$B44 -> 60 | N44: =AVERAGE(B44:M44) -> 60
A45: Itens vendidos | B45: ='Entrada de $'!B44 -> 100 | C45: ='Entrada de $'!C44 -> 100 | D45: ='Entrada de $'!D44 -> 100 | E45: ='Entrada de $'!E44 -> 100 | F45: ='Entrada de $'!F44 -> 110 | G45: ='Entrada de $'!G44 -> 110 | H45: ='Entrada de $'!H44 -> 110 | I45: ='Entrada de $'!I44 -> 120 | ... M45: ='Entrada de $'!M44 -> 100 | N45: =SUM(B45:M45) -> 1310

Sheet Saídas de $
A1: Estimativa de Saídas de Caixa com Gastos Pré-Operacionais e Despesas Operacionais
A4: Mês | B4: 0 | D4: 1 | E4: 2 | F4: 3 | G4: 4 | H4: 5 | I4: 6 | J4: 7 | K4: 8 | L4: 9 | M4: 10 | N4: 11 | O4: 12 | P4: Gastos e Despesas - Ano 01
A5: Total de Saída de Caixa | B5: =B8 -> 140000 | D5: =D19 -> 58200 | E5: =E19 -> 58200 | F5: =F19 -> 58200 | G5: =G19 -> 56800 | H5: =H19 -> 56800 | I5: =I19 -> 56800 | J5: =J19 -> 56800 | K5: =K19 -> 56800 | ... O5: =O19 -> 56800 | P5: =SUM(D5:O5) -> 685800
C7: Depreciação
A8: Gastos para criar a empresa | B8: =SUM(B9:B17) -> 140000
A9: Gastos com documentação | B9: 5000
A10: Gastos com máquinas e equipamentos | B10: 10000 | C10: =B10*0.2 -> 2000
A11: Gastos com reforma do imóvel | B11: 15000 | C11: =B11*0.1 -> 1500
A12: Gastos com móveis e utensílios | B12: 20000 | C12: =B12*0.2 -> 4000
A13: Gastos com estoque inicial | B13: 25000
A14: Outros gastos pré-operacionais | B14: 30000
A15: Lançamento da plataforma - MKT | B15: 35000
A19: Despesas com a operação | D19: =SUM(D20:D28) -> 58200 | E19: =SUM(E20:E28) -> 58200 | F19: =SUM(F20:F28) -> 58200 | G19: =SUM(G20:G28) -> 56800 | H19: =SUM(H20:H28) -> 56800 | I19: =SUM(I20:I28) -> 56800 | J19: =SUM(J20:J28) -> 56800 | K19: =SUM(K20:K28) -> 56800 | ... O19: =SUM(O20:O28) -> 56800 | P19: =SUM(D19:O19) -> 685800
A20: Despesas com salários | D20: 8600 | E20: 8600 | F20: 8600 | G20: 7200 | H20: 7200 | I20: 7200 | J20: 7200 | K20: 7200 | L20: 7200 | M20: 7200 | N20: 7200 | O20: 7200 | P20: =SUM(D20:O20) -> 90600
A21: Retirada dos sócios | D21: 7500 | E21: 7500 | F21: 7500 | G21: 7500 | H21: 7500 | I21: 7500 | J21: 7500 | K21: 7500 | L21: 7500 | M21: 7500 | N21: 7500 | O21: 7500 | P21: =SUM(D21:O21) -> 90000
A22: Despesas com marketing e vendas | D22: 4200 | E22: 4200 | F22: 4200 | G22: 4200 | H22: 4200 | I22: 4200 | J22: 4200 | K22: 4200 | L22: 4200 | M22: 4200 | N22: 4200 | O22: 4200 | P22: =SUM(D22:O22) -> 50400
A23: Despesas com equipamento/infra | D23: 6700 | E23: 6700 | F23: 6700 | G23: 6700 | H23: 6700 | I23: 6700 | J23: 6700 | K23: 6700 | L23: 6700 | M23: 6700 | N23: 6700 | O23: 6700 | P23: =SUM(D23:O23) -> 80400
A24: Aluguel | D24: 5600 | E24: 5600 | F24: 5600 | G24: 5600 | H24: 5600 | I24: 5600 | J24: 5600 | K24: 5600 | L24: 5600 | M24: 5600 | N24: 5600 | O24: 5600 | P24: =SUM(D24:O24) -> 67200
A25: Serviço de Cloud | D25: 4500 | E25: 4500 | F25: 4500 | G25: 4500 | H25: 4500 | I25: 4500 | J25: 4500 | K25: 4500 | L25: 4500 | M25: 4500 | N25: 4500 | O25: 4500 | P25: =SUM(D25:O25) -> 54000
A26: Energia Elétrica | D26: 5600 | E26: 5600 | F26: 5600 | G26: 5600 | H26: 5600 | I26: 5600 | J26: 5600 | K26: 5600 | L26: 5600 | M26: 5600 | N26: 5600 | O26: 5600 | P26: =SUM(D26:O26) -> 67200
A27: Despesas de depreciação | D27: 7500 | E27: 7500 | F27: 7500 | G27: 7500 | H27: 7500 | I27: 7500 | J27: 7500 | K27: 7500 | L27: 7500 | M27: 7500 | N27: 7500 | O27: 7500 | P27: =SUM(D27:O27) -> 90000
A28: Outras Despesas | D28: 8000 | E28: 8000 | F28: 8000 | G28: 8000 | H28: 8000 | I28: 8000 | J28: 8000 | K28: 8000 | L28: 8000 | M28: 8000 | N28: 8000 | O28: 8000 | P28: =SUM(D28:O28) -> 96000

Sheet Para exercitar
B6: Despesa com Operação | C6: Ao Mês | D6: Total Ano | F6: Despesa | H6: Valor único
B7: Retirada dos sócios | C7: 15000 | D7: =C7*12 -> 180000 | F7: Gastos para criar a empresa | H7: 75000
B8: Despesas com marketing e vendas | C8: 2000 | D8: =C8*12 -> 24000 | F8: Gastos com documentação | H8: 5000
B9: Despesas com equipamento/infra, Contabilidade, Internet, Advogados, Segurança, Limpeza, | C9: 9000 | D9: =C9*12 -> 108000 | F9: Gastos com máquinas e equipamentos | H9: 150000
B10: Aluguel | C10: 3000 | D10: =C10*12 -> 36000 | F10: Gastos com reforma do imóvel | H10: 20000
B11: Água | C11: 500 | D11: =C11*12 -> 6000 | F11: Gastos com móveis e utensílios | H11: 20000
B12: Energia Elétrica | C12: 750 | D12: =C12*12 -> 9000 | F12: Gastos com estoque inicial | H12: 70000
B13: Despesas de depreciação | C13: 3000 | D13: =C13*12 -> 36000 | F13: Outros gastos pré-operacionais | H13: 50000
B14: Outras Despesas | C14: 3000 | D14: =C14*12 -> 36000 | F14: Total de Gastos Pré-Operacionais | H14: =SUM(H7:H13) -> 390000
B15: Total de despesas com Operação | C15: =SUM(C7:C14) -> 36250 | D15: =C15*12 -> 435000

Sheet Resumo-Planejamento Financeiro
A1: Demonstração do Resultado do Exercício
B3: Ano 01 | C3: Ano 02 | D3: Ano 03 | E3: Ano 04 | F3: Ano 05
A4: Receitas Brutas | B4: ='Entrada de $'!N5 -> 947100 | C4: =B4*(1+InformacoesBasicas!D29) -> 1089165 | D4: =C4*(1+InformacoesBasicas!D30) -> 1361456.2 | E4: =D4*(1+InformacoesBasicas!D31) -> 1906038.7 | F4: =E4*(1+InformacoesBasicas!D32) -> 3049662
A5: (-) Impostos | B5: =IF(InformacoesBasicas!$B10=1,0.18,IF(InformacoesBasicas!$B10=2,0.05,IF(InformacoesBasicas!$B10=1,0.1,0.1)))*B4 -> 47355 | C5: =IF(InformacoesBasicas!$B10=1,0.18,IF(InformacoesBasicas!$B10=2,0.05,IF(InformacoesBasicas!$B10=1,0.1,0.1)))*C4 -> 54458.25 | D5: =IF(InformacoesBasicas!$B10=1,0.18,IF(InformacoesBasicas!$B10=2,0.05,IF(InformacoesBasicas!$B10=1,0.1,0.1)))*D4 -> 68072.812 | E5: =IF(InformacoesBasicas!$B10=1,0.18,IF(InformacoesBasicas!$B10=2,0.05,IF(InformacoesBasicas!$B10=1,0.1,0.1)))*E4 -> 95301.938 | F5: =IF(InformacoesBasicas!$B10=1,0.18,IF(InformacoesBasicas!$B10=2,0.05,IF(InformacoesBasicas!$B10=1,0.1,0.1)))*F4 -> 152483.1
A6: Receitas Líquidas | B6: =B4-B5 -> 899745 | C6: =C4-C5 -> 1034706.8 | D6: =D4-D5 -> 1293383.4 | E6: =E4-E5 -> 1810736.8 | F6: =F4-F5 -> 2897178.9
A7: (-)Custo das Mercadorias Vendidas | B7: ='Calculo de Custo'!N5 -> 482775 | C7: =B7*(1+InformacoesBasicas!D43) -> 531052.5 | D7: =C7*(1+InformacoesBasicas!D44) -> 610710.38 | E7: =D7*(1+InformacoesBasicas!D45) -> 732852.45 | F7: =E7*(1+InformacoesBasicas!D46) -> 916065.56
A8: (-) Despesas Operacionais | B8: ='Saídas de $'!P19 -> 685800 | C8: =B8*(1+InformacoesBasicas!D36) -> 754380 | D8: =C8*(1+InformacoesBasicas!D37) -> 867537 | E8: =D8*(1+InformacoesBasicas!D38) -> 997667.55 | F8: =E8*(1+InformacoesBasicas!D39) -> 1147317.7
A9: Resultado antes do IR | B9: =B6-B8-B7 -> -268830 | C9: =C6-C8-C7 -> -250725.75 | D9: =D6-D8-D7 -> -184863.94 | E9: =E6-E8-E7 -> 80216.812 | F9: =F6-F8-F7 -> 833795.66
A10: (-) Imposto de Renda | B10: =IF(B9>0,B9*0.25,0) -> 0 | C10: =IF(C9>0,C9*0.25,0) -> 0 | D10: =IF(D9>0,D9*0.25,0) -> 0 | E10: =IF(E9>0,E9*0.25,0) -> 20054.203 | F10: =IF(F9>0,F9*0.25,0) -> 208448.91
A11: Lucro/Prejuízo Líquido | B11: =B9-B10 -> -268830 | C11: =C9-C10 -> -250725.75 | D11: =D9-D10 -> -184863.94 | E11: =E9-E10 -> 60162.609 | F11: =F9-F10 -> 625346.74
A14: Demonstração do Fluxo de Caixa
B15: Ano 01 | C15: Ano 02 | D15: Ano 03 | E15: Ano 04 | F15: Ano 05
A16: Entradas | B16: =B4 -> 947100 | C16: =C4 -> 1089165 | D16: =D4 -> 1361456.2 | E16: =E4 -> 1906038.7 | F16: =F4 -> 3049662
A17: (-) Saídas | B17: =B5+B8+B10+B7 -> 1215930 | C17: =C5+C8+C10+C7 -> 1339890.8 | D17: =D5+D8+D10+D7 -> 1546320.2 | E17: =E5+E8+E10+E7 -> 1845876.1 | F17: =F5+F8+F10+F7 -> 2424315.3
A18: (+) Depreciação | B18: =SUM('Saídas de $'!$C$10:C$12) -> 7500 | C18: =SUM('Saídas de $'!$C$10:C$12) -> 7500 | D18: =SUM('Saídas de $'!$C$10:C$12) -> 7500 | E18: =SUM('Saídas de $'!$C$10:C$12) -> 7500 | F18: =SUM('Saídas de $'!$C$10:C$12) -> 7500
A19: Fluxo de Caixa | B19: =B16-B17+B18 -> -261330 | C19: =C16-C17+C18 -> -243225.75 | D19: =D16-D17+D18 -> -177363.94 | E19: =E16-E17+E18 -> 67662.609 | F19: =F16-F17+F18 -> 632846.74
A23: Taxa Interna de Retorno Estimada: | C23: =IRR(B56:G56) -> 0.12380223 | D23: ao ano
A55: Necessidade de Investimento | B55: Ano 0 | C55: Ano 1 | D55: Ano 2 | E55: Ano 3 | F55: Ano 4 | G55: Ano 5
A56: Fluxo de Caixa | B56: =-'Saídas de $'!B8 -> -140000 | C56: =B11+'Saídas de $'!$P27 -> -178830 | D56: =C11+'Saídas de $'!$P27 -> -160725.75 | E56: =D11+'Saídas de $'!$P27 -> -94863.938 | F56: =E11+'Saídas de $'!$P27 -> 150162.61 | G56: =F11+'Saídas de $'!$P27 -> 715346.74
