Workbook

Sheet Copetência e Caixa
B11: COMPETÊNCIA = à vista + a prazo | E11: À vista | F11: CAIXA = à vista | H11: A prazo | I11: Fluxo Projetado = a prazo
B12: Ganhar | C12: Executar, NF | D12: 1000 | E12: 0.17 | F12: Recebimento | G12: =D12*E12 -> 170 | H12: =1-E12 -> 0.83 | I12: a Receber | J12: =D12*H12 -> 830
B13: (-) Gastar | C13: Consumir | D13: 800 | E13: 0.2 | F13: (-) Pagamento | G13: =D13*E13 -> 160 | H13: =1-E13 -> 0.8 | I13: (-) a Pagar | J13: =D13*H13 -> 640
B14: LUCRO | C14: Resultado | D14: =D12-D13 -> 200 | F14: SALDO EM CAIXA | G14: =G12-G13 -> 10 | I14: SALDO A RECEBER | J14: =J12-J13 -> 190
B15: Operações a vista e a prazo | C15: Lucro Contábil | D15: 1 | F15: Operações a vista | G15: Lucro Financeiro | I15: Operações a prazo | J15: Lucro a Realizar

Sheet DRE e DFC
B11: Demonstração do Resultado do Exercício DRE = Todas as transações, sejam à vista ou a prazo, o que importa é ter acontecido dentro do período | E11: Demonstração do Fluxo de Caixa DFC = Somente as transações à vista, pois desconsidera as que foram a prazo
B12: Receita | C12: $1.000 | D12: ≠ | E12: Recebimento de 17% | F12: $170
B13: (-) Gasto | C13: ($800) | D13: ≠ | E13: (-) Pagamento de 20% | F13: ($160)
B14: Lucro | C14: $200 | D14: ≠ | E14: Saldo em Caixa | F14: $10
B15: (-) IR e CSLL de 30% x LAIR | C15: ($60) | E15: (-) IR e CSLL a Pagar | F15: ($60)
B16: Lucro Líquido do Exercício | C16: $140 | E16: Necessidade de Capital de Giro | F16: ($50)

Sheet Estrutura da DRE
A5: DEMONSTRAÇÃO DO RESULTADO DO EXERCÍCIO (Transações a Vista e a Prazo de um mesmo período) | C5: Participações sobre o Faturamento
A6: 1.Receita Bruta ou Faturamento (NF e Recibos Emitidos) | B6: 100000 | C6: 1
A7: 2. (-) Deduções (ISS, PIS/COFINS sobre a NF) | B7: =-B6*0.145 -> -14500 | C7: 5% de ISS e 9,25% PIS e COFINS = 14,5%
A8: 3. = Receita Líquida (Valor que é do Negócio, da Clínica, Consutório) | B8: =B6*0.855 -> 85500 | C8: 0.855
A9: 4. (-) Custo dos Procediemtnos Executados ou Vendidos | B9: =-B6*0.6 -> -60000 | C9: 60% Gastos com os Procedimentos
A10: Materiais e Insumos + Mão de Obra Direta na Execução + Gastos com Ambiente Produtivo
A11: 5. = Lucro Bruto (Resultado da Atividade Principal, do objeto do Contrato Social, CNAE) | B11: =B6*0.255 -> 25500 | C11: 25,50% Resultado Principal, só dos Procedimentos
A12: 6.(-) Despesas Operacionais (gastos comuns de "Suporte Empresarial, do dia a dia") | B12: =-B6*0.07 -> -7000 | C12: 7% Gastos com a parte Empresarial
A13: (-) Comerciais (esforço de venda) | B13: =-B6*0.02 -> -2000 | C13: 2% com Esforço de venda, parte Comercial
A14: (-) Administrativas (esforço burocrático) | B14: =-B6*0.05 -> -5000 | C14: 5% com Esforço burocrático, parte Administrativa
A15: + ou (-) Outras Receitas ou Despesas Operacionais | B15: 0
A16: 7. = Lucro Antes dos Juros e do Imposto de Renda (LAJIR) | B16: =B6*0.185 -> 18500 | C16: 18,50% Resiltado Operacional SEM os Juros
A17: 8. + ou (-) Resultado Financeiro Líquido (Receita Financeira (-) Despesa Financeira) | B17: =-B6*0.05 -> -5000 | C17: 5% de Juros bancários, cartões, operadoras
A18: 9. = Lucro Operacional Líquido ou Lucro Antes do Imposto de Renda | B18: =B6*0.135 -> 13500 | C18: 13,50% de Resultado Operacional
A19: 10. (-) Provisão para Imposto de Renda e Contribuição Social de Lucro Líquido | B19: =-B18*0.3 -> -4050 | C19: 4,05% de Impostos Federais
A20: 11. = Lucro Líquido do Exercício (Resultado Final para os Sócios ou crescimento da Empresa) | B20: =B6*0.0945 -> 9450 | C20: 9,45% de Lucro de Remuneração ou de crescimento

Sheet Estrutura do Fluxo de Caixa 
B2: PLANILHA DE FLUXO DE CAIXA
C3: Período Desejado pelo Gestor: DIA, SEMANA, QUINZENA, MÊS
C4: 1 | D4: 2 | E4: 3 | F4: 4 | G4: 5 | H4: 6 | I4: 7 | J4: 8 | K4: 9 | L4: 10 | M4: 11 | N4: 12
B5: R E C E B I M E N T O S OU E N T R A D A S
B6: RELACIONE SEUS RECEBIMENTOS EM DINHEIRO OU PIX
B7: Procedimentos realizados à vista
B8: Operadoras de transações passadas e a prazo
B9: Cartões de Crédito
B10: Cheques Pré datados
B11: Aporte de Capital de Sócios
B12: Empréstimos Bancários Contraídos
B13: Venda ou Alienação de Equipamentos, Máquinas, Móveis
B14: Outros recebimentos
B15: TOTAL DOS RECEBIMENTOS OU ENTRADAS | C15: =SUM(C7:C14) -> 0 | D15: =SUM(D7:D14) -> 0 | E15: =SUM(E7:E14) -> 0 | F15: =SUM(F7:F14) -> 0 | G15: =SUM(G7:G14) -> 0 | H15: =SUM(H7:H14) -> 0 | I15: =SUM(I7:I14) -> 0 | J15: =SUM(J7:J14) -> 0 | ... N15: =SUM(N7:N14) -> 0
B16: P A G A M E N T O S OU S A Í D A S
B17: RELACIONE SEUS PAGAMENTOS EM DINHEIRO OU PIX
B18: Aquisições a vista de Inumos e Medicamentos
B19: Aquisições a prazo no passado de Insumos e Medicamentos
B20: Folha de pagamento dos Colaboradores
B21: INSS Patronal
B22: FGTS
B23: Férias
B24: 13º salário
B25: Verbas para rescisão
B26: Manutenção Predial e de Bens
B27: Aluguél, Condomínio, IPTU
... B39: Outros pagamentos
B40: TOTAL DOS PAGAMENTOS OU SAÍDAS | C40: =SUM(C18:C39) -> 0 | D40: =SUM(D18:D39) -> 0 | E40: =SUM(E18:E39) -> 0 | F40: =SUM(F18:F39) -> 0 | G40: =SUM(G18:G39) -> 0 | H40: =SUM(H18:H39) -> 0 | I40: =SUM(I18:I39) -> 0 | J40: =SUM(J18:J39) -> 0 | ... N40: =SUM(N18:N39) -> 0
B41: 1 SALDO DOS MOVIMENTOS DO DIA, SEMANA, QUINZENA OU MÊS | C41: =C15-C40 -> 0 | D41: =D15-D40 -> 0 | E41: =E15-E40 -> 0 | F41: =F15-F40 -> 0 | G41: =G15-G40 -> 0 | H41: =H15-H40 -> 0 | I41: =I15-I40 -> 0 | J41: =J15-J40 -> 0 | ... N41: =N15-N40 -> 0
B42: 2 SALDO ANTERIOR | C42: 0 | D42: =C45 -> 0 | E42: =D45 -> 1 | F42: =E45 -> 5 | G42: =F45 -> 5 | H42: =G45 -> 5 | I42: =H45 -> 5 | J42: =I45 -> 5 | K42: =J45 -> 5 | ... N42: =M45 -> 5
B43: 3 SALDO ACUMULADO (1 + 2 ) | C43: =C41+C42 -> 0 | D43: =D41+D42 -> 0 | E43: =E41+E42 -> 1 | F43: =F41+F42 -> 5 | G43: =G41+G42 -> 5 | H43: =H41+H42 -> 5 | I43: =I41+I42 -> 5 | J43: =J41+J42 -> 5 | ... N43: =N41+N42 -> 5
B44: 4 NECESSIDADE EMPRÉSTIMOS PARA CAPITAL DE GIRO | C44: 0 | D44: 1 | E44: 4
B45: 5 SALDO FINAL (3 + 4) | C45: =C43+C44 -> 0 | D45: =D43+D44 -> 1 | E45: =E43+E44 -> 5 | F45: =F43+F44 -> 5 | G45: =G43+G44 -> 5 | H45: =H43+H44 -> 5 | I45: =I43+I44 -> 5 | J45: =J43+J44 -> 5 | ... N45: =N43+N44 -> 5

Sheet PEq
G6: Centros de Custos por Preço da mesma Consulta
G7: Particular | H7: Operadora 1 | I7: Operadora 2 | J7: Operadora 3 | K7: Operadora 4
E8: Preço da Consulta | G8: 250 | H8: 125 | I8: 100 | J8: 75 | K8: 40
E9: (-) Custo da Consulta | G9: =SUM(F10:F12) -> 70 | H9: =SUM(F10:F12) -> 70 | I9: =SUM(F10:F12) -> 70 | J9: =SUM(F10:F12) -> 70 | K9: =SUM(F10:F12) -> 70
E10: com Materiais insumos aplicados no paciente | F10: 5
E11: com o tempo de 20 minutos de Mão de Obra de Execução do profissional de saúde | F11: 60
E12: com o tempo de 20 minutos de Energia | F12: 5
E13: Margem de Contribuição ou seja, Resultado de cada Consulta ou Procedimento | G13: =G8-G9 -> 180 | H13: =H8-H9 -> 55 | I13: =I8-I9 -> 30 | J13: =J8-J9 -> 5 | K13: =K8-K9 -> -30 | L13: =SUM(G13:J13) -> 270
E14: Participação do Rateio por arbítrio do Gestor (recomendamos usar um direcionador com aderência de consumo) | G14: =G13/L13 -> 0.66666667 | H14: =H13/L13 -> 0.2037037 | I14: =I13/L13 -> 0.11111111 | J14: =J13/L13 -> 0.018518519
E15: Gastos Fixos de um Consultório em Bairro de Classe Média por mês já Rateados por Centro de Custos | G15: =F33*G14 -> 7898.3889 | H15: =F33*H14 -> 2413.3966 | I15: =F33*I14 -> 1316.3981 | J15: =F33*J14 -> 219.39969 | L15: =SUM(G15:K15) -> 11847.583
E16: Quantidade Mensal de Consultas do Ponto de Equilíbrio por Centro de Custos = (Fixos / Margem de Contribuição Unit) | G16: =G15/G13 -> 43.879938 | H16: =H15/H13 -> 43.879938 | I16: =I15/I13 -> 43.879938 | J16: =J15/J13 -> 43.879938
E20: Gastos Fixos de um Consultório em Bairro de Classe Média por mês
B21: Secretária | E21: Secretária, encargos trabalhistas, provisões com 13 salário e férias, Salário Bruto de 1.500 | F21: =C29 -> 2414.25
B22: Salário Bruto | C22: 1500 | E22: Aluguel | F22: 2500
B23: INSS | C23: =C22*0.22 -> 330 | E23: Condomínio | F23: 1500
B24: FGTS | C24: =C22*0.08 -> 120 | E24: IPTU do Consultório | F24: 300
B25: Multa FGTS | C25: =C24*0.4 -> 48 | E25: Internet | F25: 300
B26: Aviso Prévio | C26: =C22/12 -> 125 | E26: Propaganda | F26: 500
B27: 13 Salário | C27: =C22/12 -> 125 | E27: Limpeza | F27: 800
B28: Férias | C28: =(C22/12)*1.33 -> 166.25 | E28: Depreciação dos Imobilizados | F28: =I36 -> 2833.3333 | H28: Depreciação ou Desgastes
B29: Soma | C29: =SUM(C22:C28) -> 2414.25 | E29: Coleta | F29: 200 | H29: Móveis | I29: 140000
E30: Sistema Informatizado (agendamento, prontuário...) | F30: 300 | H30: Equipamentos | I30: 200000
E31: Outros gastos para suplementar algum acima insuficiente | F31: 200 | H31: Total | I31: =SUM(I29:I30) -> 340000
H32: Tempo de Vida útil | I32: 10 anos
E33: Total dos Gastos Fixos por mês | F33: =SUM(F21:F32) -> 11847.583 | H33: Taxas de Depreciação:
H34: Anual | I34: 0.1
E35: Total dos Gastos Fixos por Ano | F35: =F33*12 -> 142171 | H35: Mensal | I35: =I34/12 -> 0.0083333333
H36: Valor Mensal | I36: =I31*I35 -> 2833.3333

Sheet %BP
B5: BALANÇO PATRIMONIAL
B7: ATIVO | D7: PASSIVO | I7: ATIVO | K7: PASSIVO
B9: CIRCULANTE | C9: 1235249 | D9: CIRCULANTE | E9: 1423381.5 | I9: CIRCULANTE | J9: 1235249 | K9: CIRCULANTE | L9: 1423381.5
B10: Caixa | C10: 8806 | D10: Fornecedores | E10: 301261 | I10: =SUM(C9/C28) -> 0.14397909 | K10: =L9/L28 -> 0.16590758
B11: Aplicações financeiras | C11: 201371 | D11: Salários a pagar | E11: 91045
B12: Clientes | C12: 346113 | D12: Impostos a recolher | E12: 92605
B13: Mercadoria | C13: 563167 | D13: Provisão de IR (DRE) | E13: 72082.5
B14: Seguros pagos antecipad/ | C14: 115792 | D14: Empréstimos bancários | E14: 866388
B16: NÃO CIRCULANTE | C16: 7344115 | D16: NÃO CIRCULANTE | E16: 3734218 | I16: Realizável a Longo Prazo | J16: 1312662 | K16: NÃO CIRCULANTE | L16: 3734218
B17: Realizável a Longo Prazo | D17: Debêntures emitidas | E17: 478559 | I17: =C16/C28 -> 0.85602091 | K17: =L16/L28 -> 0.43525581
B18: Empréstimos a controladas | C18: 1312662 | D18: Financiamento em 240 meses | E18: 2022952
D19: Tributos parcelados a LP | E19: 219545
D20: Notas promissórias a LP | E20: 488138
D21: Passivo contingencial a L P | E21: 525024
B23: PERMANENTE | D23: PATRIMÔNIO LÍQUIDO | E23: 3421764.5 | I23: PERMANENTE | J23: =SUM(C24:C26) -> 6031453 | K23: PATRIMÔNIO LÍQUIDO | L23: 3421764.5
B24: Investimentos em colig e contr | C24: 1266486 | D24: Capital | E24: 1221000 | I24: =J23/J28 -> 0.70301866 | K24: =L23/L28 -> 0.39883662
B25: Imobilizado | C25: 3872067 | D25: Reservas de Capital | E25: 1000276
B26: Intangível | C26: 892900 | D26: Reservas de Lucros | E26: 1042000
D27: Lucro do Exercício (DRE) | E27: 158488.5
B28: TOTAL | C28: 8579364 | D28: TOTAL | E28: 8579364 | I28: TOTAL | J28: 8579364 | K28: TOTAL | L28: 8579364

Sheet % DRE
B2: DEMONSTRAÇÃO DO RESULTADO DO EXERCÍCIO
B3: Receita Bruta | C3: 2394514
B4: (-) Deduções (impostos sobre vendas) | C4: -202178 | D4: %
B5: Receita Líquida | C5: =SUM(C3:C4) -> 2192336 | D5: 1 | F5: % = (Cada Conta / Receita Liquida) X 100
B6: (-) Custo de Produtos Vendidos (C P V) | C6: -1300000 | D6: =C6/C5*100 -> -59.29748
B7: LUCRO BRUTO | C7: 892336 | D7: =C7/C5*100 -> 40.70252 | E7: Margem Bruta
B8: (-) Despesas Operacionais | C8: =SUM(C9:C10) -> -170641 | D8: =C8/C5*100 -> -7.7835241
B9: Comerciais ou com Vendas | C9: -49532 | D9: =C9/C5*100 -> -2.2593252
B10: Administrativas = 47.009 + 62.170 + 11.930 = | C10: -121109 | D10: =C10/C5*100 -> -5.5241988
B11: + Outras Receitas Operacionais "Aluguel / Estacionamento" | C11: 41000 | D11: =C11/C5*100 -> 1.8701513
B12: Lucro Antes dos Juros e do Imposto de Renda (LAJIR) | C12: =SUM(C7,C8,C11) -> 762695 | D12: =C12/C5*100 -> 34.789147
B13: (-) Despesas Financeiras= juros passivos | C13: -504828 | D13: =C13/C5*100 -> -23.026945
B14: LUCRO OPERACIONAL LÍQUIDO | C14: =SUM(C12:C13) -> 257867 | D14: =C14/C5*100 -> 11.762203 | E14: Margem Operacional Líquida
B15: (-) Resultado Não Operacional "Perda na Alienacao" | C15: -17592 | D15: =C15/C5*100 -> -0.80243174
B16: LUCRO ANTES DO IR (LAIR) | C16: =SUM(C14:C15) -> 240275 | D16: =C16/C5*100 -> 10.959771
B17: (-) Provisão de IR e CS (30% sobre LAIR) | C17: -72082.5 | D17: =C17/C5*100 -> -3.2879312
B18: LUCRO DEPOIS DO IR E CS | C18: 168192.5 | D18: =C18/C5*100 -> 7.6718395
B19: (-) Participações de empregados | C19: -9704 | D19: =C19/C5*100 -> -0.44263288
B20: LUCRO LÍQUIDO DO EXERCÍCIO | C20: =SUM(C18:C19) -> 158488.5 | D20: =C20/C5*100 -> 7.2292067 | E20: Margem Líquida de Lucro

Sheet Liquidez
B4: Índices de Liquidez | C4: Interpretações | D4: Fórmulas | E4: 2024 | F4: Padrão | G4: Variação | H4: Perfil (Qualificação de cada Índice)
B5: Qto maior, melhor | G5: % | H5: Insatisfatório | I5: Razoável | J5: Satisfatório | K5: Bom | L5: Ótimo
H6: 0.3001 | I6: 0.1001 | J6: 0 | K6: 0.1001 | L6: 0.3001
B7: Liquidez Seca | C7: SEM ESTOQUE consegue pagar suas dívidas de um ano? | D7: (AC – EST) / PC | E7: =('%BP'!C9-'%BP'!C13)/'%BP'!E9 -> 0.47217278 | F7: 0.35 | G7: =(E7/F7)-1 -> 0.34906509
B9: Liquidez Corrente | C9: DURANTE UM ANO consegue pagar suas dívidas? | D9: AC / PC | E9: ='%BP'!C9/'%BP'!E9 -> 0.86782707 | F9: 1.02 | G9: =(E9/F9)-1 -> -0.14918914
B11: Liquidez Geral | C11: NO FUTURO conseguirá pagar suas dívidas? | D11: (AC + ARLP) / | E11: =('%BP'!J9+'%BP'!J16)/('%BP'!L9+'%BP'!L16) -> 0.49401102 | F11: 0.44 | G11: =(E11/F11)-1 -> 0.12275232
D12: (PC + PNC)

Sheet Rentabilidade
B3: Índices de Rentabilidade | C3: Interpretações | D3: Fórmulas | E3: 2024 | F3: Padrão | G3: Variação | H3: Perfil (Qualificação de cada Índice)
B4: Qto maior, melhor | G4: % | H4: Insatisfatório | I4: Razoável | J4: Satisfatório | K4: Bom | L4: Ótimo
H5: 0.3001 | I5: 0.1001 | J5: 0 | K5: 0.1001 | L5: 0.3001
B6: Rentabilidade do Capital Próprio ou PL | C6: Quanto o Lucro representa do Patrimônio Líquido | D6: (LLEx / PL) x 100 | E6: ='% DRE'!C20/'%BP'!L23 -> 0.04631777 | F6: 0.07 | G6: =E6/F6-1 -> -0.33831758
B7: Rentabilidade do Ativo ou dos Investimentos ou TIR | C7: Quanto o Lucro representa do Ativo | D7: (LLEx / A) x 100 | E7: ='% DRE'!C20/'%BP'!J28 -> 0.018473222 | F7: 0.035 | G7: =E7/F7-1 -> -0.47219364
B8: Margem Bruta | C8: Qto o Lucro Bruto representa da Receita (atividade Fim) | D8: Lucro Bruto | E8: ='% DRE'!C7/'% DRE'!C5 -> 0.4070252 | F8: 0.35 | G8: =E8/F8-1 -> 0.16292914
D9: Receita
D10: x 100
B11: Margem Operacional de Lucro | C11: Qto o Lucro Operacional representa da Receita (atividade Meio) | D11: L Oper Líq | E11: ='% DRE'!C14/'% DRE'!C5 -> 0.11762203 | F11: 0.11 | G11: =E11/F11-1 -> 0.069291137
D12: Receita
D13: x 100
B14: Margem Líquida de Lucro | C14: Qto o Lucro Líquido representa da Receita | D14: L L Ex | E14: ='% DRE'!C20/'% DRE'!C5 -> 0.072292067 | F14: 0.0695 | G14: =E14/F14-1 -> 0.040173619
D15: Receita
D16: x 100

Sheet EBTIDA
E4: Lucro Antes dos Juros e do Imposto de Renda ou LAJIR | F4: 745103 | G4: 0.3399
E5: + ou (-) Resultado Financeiro (receita financeira (-) despesa financeira) | F5: -504828 | G5: -0.2303
E6: Lucro Operacional Líquido ou LAIR = Margem Op de Lucro | F6: =SUM(F4:F5) -> 240275 | G6: =SUM(G4:G5) -> 0.1096
E10: Lucro Antes dos Juros e do Imposto de Renda ou LAJIR | F10: 745103 | G10: 0.3399
E11: + ou (-) Resultado Financeiro (receita financeira (-) despesa financeira) | F11: 0 | G11: 0
E12: Lucro Operacional Líquido ou LAIR = Margem Op de Lucro | F12: =SUM(F10:F11) -> 745103 | G12: =SUM(G10:G11) -> 0.3399
E17: Lucro Antes dos Juros e do Imposto de Renda ou LAJIR | F17: 745103 | G17: 0.3399
E18: + Depreciação do período
E19: Custo de Produção (nos Bens de uso nos Procedimentos) .......... | F19: 30000 | G19: 0.0181
E20: Despesas Operacionais (nos Bens de uso Comerc e Admin)........ | F20: 10000
E21: + Amortizações do período (Bens Intangíveis).................................... | F21: 0
E22: EBTIDA (Lucros antes de Juros, Impostos, Depreciação e Amortização) | F22: =SUM(F17:F21) -> 785103 | G22: =SUM(G17:G20) -> 0.358
